{
    "questions": [
      {
        "id": 1,
        "questionText": "როდის მოხდა დიდგორის ბროძალა?",
        "answers": ["1121", "1131", "1241", "1124"],
        "correctAnswer": "1121"
      },
      {
        "id": 2,
        "questionText": "ვინ იყო დამოუკიდებელი საქართველოს პირველი მეფე?",
        "answers":["დავით აღმაშენებელი","გიორგი II","ბაგრატ III","ერეკლე II"],
        "correctAnswer":"ბაგრატ III"
      },
      {
        "id": 3,
        "questionText":"რომელ საუკუნეში იყო საქართველოს ოქროს ხანა?",
        "answers":["XII","X","XIII","IX"],
        "correctAnswer":"XII"
      },
      {
        "id":4,
        "questionText":"რამდენია თერთმეტის კვადრატს დამატებული თერთმეტი?",
        "answers":["143","111","137","132"],
        "correctAnswer":"132"
      },
      {
        "id":5,
        "questionText":"რომელია მზის სისტემის მესამე პლანეტა?",
        "answers":["სატურნი","დედამიწა","ურანი","ნეპტუნი"],
        "correctAnswer":"დედამიწა"
      },
      {
        "id":6,
        "questionText":"რომელმა ქვეყანამ მოიგო 2022 წლის ფეხბურთის მსოფლიო ჩემპიონატი?",
        "answers":["ხორვატია","საფრანგეთი","ნიდერლანდები","არგენტინა"],
        "correctAnswer":"არგენტინა"
      },
      {
        "id":7,
        "questionText":"რომელმა ქვეყანამ მოიგო 2016 წლის ფეხბურთის ევროპის ჩემპიონატი?",
        "answers":["პორტუგალია","იტალია","გერმანია","საფრანგეთი"],
        "correctAnswer":"პორტუგალია"
      },
      {
        "id":8,
        "questionText":"რომელია მსოფლიო ისტორიაში საუკეთესო ფეხბურთელი?",
        "answers":["კრისტიანო რონალდო","ლიონელ მესი","ჯორჯ ბესტი","ნიკოლოზ დვალიშვილი"],
        "correctAnswer":"ლიონელ მესი"
      }
      
    ]
  }
  